pyVisor/__init__.py
pyVisor/getHtmlObjects.py
pyVisor/getObj.py
pyVisor/pyVisorCLI.py
pyVisor/render.py
pyVisor/viewContent.py
pyVisor/viewVoid.py
pyVisor/pp/__init__.py
pyvisor-1.2.0.dist-info/licenses/LICENSE
pyvisor-1.2.0.dist-info/METADATA
pyvisor-1.2.0.dist-info/WHEEL
pyvisor-1.2.0.dist-info/entry_points.txt
pyvisor-1.2.0.dist-info/top_level.txt
pyvisor-1.2.0.dist-info/RECORD
