Metadata-Version: 2.4
Name: pyVisor
Version: 1.2.0
Summary: package for simple exploring of python objects
Home-page: https://edwinsaul.com/index.html?p=pyVisor
Author: Edwin Saul
Author-email: edwinsaul@proton.me
Keywords: DEV debug flask
License-File: LICENSE
Requires-Dist: flask
Dynamic: author
Dynamic: author-email
Dynamic: description
Dynamic: description-content-type
Dynamic: home-page
Dynamic: keywords
Dynamic: license-file
Dynamic: requires-dist
Dynamic: summary
